{
  "version": 1,
  "animation": "runB_Back",
  "width": 1489,
  "height": 65,
  "offsetX": -23,
  "offsetY": 0,
  "frames": [
    {
      "id": "runB_Back_0",
      "x": 1,
      "y": 1,
      "width": 47,
      "height": 63,
      "offsetX": 0,
      "offsetY": 0
    },
    {
      "id": "runB_Back_1",
      "x": 49,
      "y": 1,
      "width": 47,
      "height": 63,
      "offsetX": 0,
      "offsetY": 0
    },
    {
      "id": "runB_Back_2",
      "x": 97,
      "y": 1,
      "width": 47,
      "height": 63,
      "offsetX": 0,
      "offsetY": 0
    },
    {
      "id": "runB_Back_3",
      "x": 145,
      "y": 1,
      "width": 47,
      "height": 63,
      "offsetX": 0,
      "offsetY": 0
    },
    {
      "id": "runB_Back_4",
      "x": 193,
      "y": 1,
      "width": 47,
      "height": 63,
      "offsetX": 0,
      "offsetY": 0
    },
    {
      "id": "runB_Back_5",
      "x": 241,
      "y": 1,
      "width": 47,
      "height": 63,
      "offsetX": 0,
      "offsetY": 0
    },
    {
      "id": "runB_Back_6",
      "x": 289,
      "y": 1,
      "width": 47,
      "height": 63,
      "offsetX": 0,
      "offsetY": 0
    },
    {
      "id": "runB_Back_7",
      "x": 337,
      "y": 1,
      "width": 47,
      "height": 63,
      "offsetX": 0,
      "offsetY": 0
    },
    {
      "id": "runB_Back_8",
      "x": 385,
      "y": 1,
      "width": 47,
      "height": 63,
      "offsetX": 0,
      "offsetY": 0
    },
    {
      "id": "runB_Back_9",
      "x": 433,
      "y": 1,
      "width": 47,
      "height": 63,
      "offsetX": 0,
      "offsetY": 0
    },
    {
      "id": "runB_Back_10",
      "x": 481,
      "y": 1,
      "width": 47,
      "height": 63,
      "offsetX": 0,
      "offsetY": 0
    },
    {
      "id": "runB_Back_11",
      "x": 529,
      "y": 1,
      "width": 47,
      "height": 63,
      "offsetX": 0,
      "offsetY": 0
    },
    {
      "id": "runB_Back_12",
      "x": 577,
      "y": 1,
      "width": 47,
      "height": 63,
      "offsetX": 0,
      "offsetY": 0
    },
    {
      "id": "runB_Back_13",
      "x": 625,
      "y": 1,
      "width": 47,
      "height": 63,
      "offsetX": 0,
      "offsetY": 0
    },
    {
      "id": "runB_Back_14",
      "x": 673,
      "y": 1,
      "width": 47,
      "height": 63,
      "offsetX": 0,
      "offsetY": 0
    },
    {
      "id": "runB_Back_15",
      "x": 721,
      "y": 1,
      "width": 47,
      "height": 63,
      "offsetX": 0,
      "offsetY": 0
    },
    {
      "id": "runB_Back_16",
      "x": 769,
      "y": 1,
      "width": 47,
      "height": 63,
      "offsetX": 0,
      "offsetY": 0
    },
    {
      "id": "runB_Back_17",
      "x": 817,
      "y": 1,
      "width": 47,
      "height": 63,
      "offsetX": 0,
      "offsetY": 0
    },
    {
      "id": "runB_Back_18",
      "x": 865,
      "y": 1,
      "width": 47,
      "height": 63,
      "offsetX": 0,
      "offsetY": 0
    },
    {
      "id": "runB_Back_19",
      "x": 913,
      "y": 1,
      "width": 47,
      "height": 63,
      "offsetX": 0,
      "offsetY": 0
    },
    {
      "id": "runB_Back_20",
      "x": 961,
      "y": 1,
      "width": 47,
      "height": 63,
      "offsetX": 0,
      "offsetY": 0
    },
    {
      "id": "runB_Back_21",
      "x": 1009,
      "y": 1,
      "width": 47,
      "height": 63,
      "offsetX": 0,
      "offsetY": 0
    },
    {
      "id": "runB_Back_22",
      "x": 1057,
      "y": 1,
      "width": 47,
      "height": 63,
      "offsetX": 0,
      "offsetY": 0
    },
    {
      "id": "runB_Back_23",
      "x": 1105,
      "y": 1,
      "width": 47,
      "height": 63,
      "offsetX": 0,
      "offsetY": 0
    },
    {
      "id": "runB_Back_24",
      "x": 1153,
      "y": 1,
      "width": 47,
      "height": 63,
      "offsetX": 0,
      "offsetY": 0
    },
    {
      "id": "runB_Back_25",
      "x": 1201,
      "y": 1,
      "width": 47,
      "height": 63,
      "offsetX": 0,
      "offsetY": 0
    },
    {
      "id": "runB_Back_26",
      "x": 1249,
      "y": 1,
      "width": 47,
      "height": 63,
      "offsetX": 0,
      "offsetY": 0
    },
    {
      "id": "runB_Back_27",
      "x": 1297,
      "y": 1,
      "width": 47,
      "height": 63,
      "offsetX": 0,
      "offsetY": 0
    },
    {
      "id": "runB_Back_28",
      "x": 1345,
      "y": 1,
      "width": 47,
      "height": 63,
      "offsetX": 0,
      "offsetY": 0
    },
    {
      "id": "runB_Back_29",
      "x": 1393,
      "y": 1,
      "width": 47,
      "height": 63,
      "offsetX": 0,
      "offsetY": 0
    },
    {
      "id": "runB_Back_30",
      "x": 1441,
      "y": 1,
      "width": 47,
      "height": 63,
      "offsetX": 0,
      "offsetY": 0
    }
  ],
  "frameOrder": [
    "runB_Back_0",
    "runB_Back_1",
    "runB_Back_2",
    "runB_Back_3",
    "runB_Back_4",
    "runB_Back_5",
    "runB_Back_6",
    "runB_Back_7",
    "runB_Back_8",
    "runB_Back_9",
    "runB_Back_10",
    "runB_Back_11",
    "runB_Back_12",
    "runB_Back_13",
    "runB_Back_14",
    "runB_Back_15",
    "runB_Back_16",
    "runB_Back_17",
    "runB_Back_18",
    "runB_Back_19",
    "runB_Back_20",
    "runB_Back_21",
    "runB_Back_22",
    "runB_Back_23",
    "runB_Back_24",
    "runB_Back_25",
    "runB_Back_26",
    "runB_Back_27",
    "runB_Back_28",
    "runB_Back_29",
    "runB_Back_30",
    "runB_Back_31",
    "runB_Back_32"
  ],
  "duplicates": {
    "runB_Back_31": "runB_Back_30",
    "runB_Back_32": "runB_Back_30"
  },
  "fps": 60
}