{
  "version": 1,
  "animation": "carring_CL",
  "width": 1001,
  "height": 54,
  "offsetX": -34.6,
  "offsetY": 0,
  "frames": [
    {
      "id": "carring_CL_0",
      "x": 1,
      "y": 1,
      "width": 49,
      "height": 52,
      "offsetX": 0,
      "offsetY": 0
    },
    {
      "id": "carring_CL_1",
      "x": 51,
      "y": 1,
      "width": 49,
      "height": 52,
      "offsetX": 0,
      "offsetY": 0
    },
    {
      "id": "carring_CL_2",
      "x": 101,
      "y": 1,
      "width": 49,
      "height": 52,
      "offsetX": 0,
      "offsetY": 0
    },
    {
      "id": "carring_CL_3",
      "x": 151,
      "y": 1,
      "width": 49,
      "height": 52,
      "offsetX": 0,
      "offsetY": 0
    },
    {
      "id": "carring_CL_4",
      "x": 201,
      "y": 1,
      "width": 49,
      "height": 52,
      "offsetX": 0,
      "offsetY": 0
    },
    {
      "id": "carring_CL_5",
      "x": 251,
      "y": 1,
      "width": 49,
      "height": 52,
      "offsetX": 0,
      "offsetY": 0
    },
    {
      "id": "carring_CL_6",
      "x": 301,
      "y": 1,
      "width": 49,
      "height": 52,
      "offsetX": 0,
      "offsetY": 0
    },
    {
      "id": "carring_CL_7",
      "x": 351,
      "y": 1,
      "width": 49,
      "height": 52,
      "offsetX": 0,
      "offsetY": 0
    },
    {
      "id": "carring_CL_8",
      "x": 401,
      "y": 1,
      "width": 49,
      "height": 52,
      "offsetX": 0,
      "offsetY": 0
    },
    {
      "id": "carring_CL_9",
      "x": 451,
      "y": 1,
      "width": 49,
      "height": 52,
      "offsetX": 0,
      "offsetY": 0
    },
    {
      "id": "carring_CL_10",
      "x": 501,
      "y": 1,
      "width": 49,
      "height": 52,
      "offsetX": 0,
      "offsetY": 0
    },
    {
      "id": "carring_CL_11",
      "x": 551,
      "y": 1,
      "width": 49,
      "height": 52,
      "offsetX": 0,
      "offsetY": 0
    },
    {
      "id": "carring_CL_12",
      "x": 601,
      "y": 1,
      "width": 49,
      "height": 52,
      "offsetX": 0,
      "offsetY": 0
    },
    {
      "id": "carring_CL_15",
      "x": 651,
      "y": 1,
      "width": 49,
      "height": 52,
      "offsetX": 0,
      "offsetY": 0
    },
    {
      "id": "carring_CL_16",
      "x": 701,
      "y": 1,
      "width": 49,
      "height": 52,
      "offsetX": 0,
      "offsetY": 0
    },
    {
      "id": "carring_CL_17",
      "x": 751,
      "y": 1,
      "width": 49,
      "height": 52,
      "offsetX": 0,
      "offsetY": 0
    },
    {
      "id": "carring_CL_18",
      "x": 801,
      "y": 1,
      "width": 49,
      "height": 52,
      "offsetX": 0,
      "offsetY": 0
    },
    {
      "id": "carring_CL_19",
      "x": 851,
      "y": 1,
      "width": 49,
      "height": 52,
      "offsetX": 0,
      "offsetY": 0
    },
    {
      "id": "carring_CL_20",
      "x": 901,
      "y": 1,
      "width": 49,
      "height": 52,
      "offsetX": 0,
      "offsetY": 0
    },
    {
      "id": "carring_CL_21",
      "x": 951,
      "y": 1,
      "width": 49,
      "height": 52,
      "offsetX": 0,
      "offsetY": 0
    }
  ],
  "frameOrder": [
    "carring_CL_0",
    "carring_CL_1",
    "carring_CL_2",
    "carring_CL_3",
    "carring_CL_4",
    "carring_CL_5",
    "carring_CL_6",
    "carring_CL_7",
    "carring_CL_8",
    "carring_CL_9",
    "carring_CL_10",
    "carring_CL_11",
    "carring_CL_12",
    "carring_CL_13",
    "carring_CL_14",
    "carring_CL_15",
    "carring_CL_16",
    "carring_CL_17",
    "carring_CL_18",
    "carring_CL_19",
    "carring_CL_20",
    "carring_CL_21",
    "carring_CL_22",
    "carring_CL_23",
    "carring_CL_24",
    "carring_CL_25",
    "carring_CL_26",
    "carring_CL_27",
    "carring_CL_28",
    "carring_CL_29",
    "carring_CL_30",
    "carring_CL_31",
    "carring_CL_32"
  ],
  "duplicates": {
    "carring_CL_13": "carring_CL_12",
    "carring_CL_14": "carring_CL_12",
    "carring_CL_22": "carring_CL_21",
    "carring_CL_23": "carring_CL_21",
    "carring_CL_24": "carring_CL_21",
    "carring_CL_25": "carring_CL_21",
    "carring_CL_26": "carring_CL_21",
    "carring_CL_27": "carring_CL_21",
    "carring_CL_28": "carring_CL_21",
    "carring_CL_29": "carring_CL_21",
    "carring_CL_30": "carring_CL_21",
    "carring_CL_31": "carring_CL_21",
    "carring_CL_32": "carring_CL_21"
  },
  "fps": 60
}