{
  "version": 1,
  "animation": "runR",
  "width": 4066,
  "height": 748,
  "offsetX": -145.35,
  "offsetY": 0,
  "frames": [
    {
      "id": "runR_0",
      "x": 1,
      "y": 1,
      "width": 270,
      "height": 248,
      "offsetX": 0,
      "offsetY": 0
    },
    {
      "id": "runR_1",
      "x": 272,
      "y": 1,
      "width": 270,
      "height": 248,
      "offsetX": 0,
      "offsetY": 0
    },
    {
      "id": "runR_2",
      "x": 543,
      "y": 1,
      "width": 270,
      "height": 248,
      "offsetX": 0,
      "offsetY": 0
    },
    {
      "id": "runR_3",
      "x": 814,
      "y": 1,
      "width": 270,
      "height": 248,
      "offsetX": 0,
      "offsetY": 0
    },
    {
      "id": "runR_4",
      "x": 1085,
      "y": 1,
      "width": 270,
      "height": 248,
      "offsetX": 0,
      "offsetY": 0
    },
    {
      "id": "runR_5",
      "x": 1356,
      "y": 1,
      "width": 270,
      "height": 248,
      "offsetX": 0,
      "offsetY": 0
    },
    {
      "id": "runR_6",
      "x": 1627,
      "y": 1,
      "width": 270,
      "height": 248,
      "offsetX": 0,
      "offsetY": 0
    },
    {
      "id": "runR_7",
      "x": 1898,
      "y": 1,
      "width": 270,
      "height": 248,
      "offsetX": 0,
      "offsetY": 0
    },
    {
      "id": "runR_8",
      "x": 2169,
      "y": 1,
      "width": 270,
      "height": 248,
      "offsetX": 0,
      "offsetY": 0
    },
    {
      "id": "runR_9",
      "x": 2440,
      "y": 1,
      "width": 270,
      "height": 248,
      "offsetX": 0,
      "offsetY": 0
    },
    {
      "id": "runR_10",
      "x": 2711,
      "y": 1,
      "width": 270,
      "height": 248,
      "offsetX": 0,
      "offsetY": 0
    },
    {
      "id": "runR_11",
      "x": 2982,
      "y": 1,
      "width": 270,
      "height": 248,
      "offsetX": 0,
      "offsetY": 0
    },
    {
      "id": "runR_12",
      "x": 3253,
      "y": 1,
      "width": 270,
      "height": 248,
      "offsetX": 0,
      "offsetY": 0
    },
    {
      "id": "runR_13",
      "x": 3524,
      "y": 1,
      "width": 270,
      "height": 248,
      "offsetX": 0,
      "offsetY": 0
    },
    {
      "id": "runR_14",
      "x": 3795,
      "y": 1,
      "width": 270,
      "height": 248,
      "offsetX": 0,
      "offsetY": 0
    },
    {
      "id": "runR_15",
      "x": 1,
      "y": 250,
      "width": 270,
      "height": 248,
      "offsetX": 0,
      "offsetY": 0
    },
    {
      "id": "runR_16",
      "x": 272,
      "y": 250,
      "width": 270,
      "height": 248,
      "offsetX": 0,
      "offsetY": 0
    },
    {
      "id": "runR_17",
      "x": 543,
      "y": 250,
      "width": 270,
      "height": 248,
      "offsetX": 0,
      "offsetY": 0
    },
    {
      "id": "runR_18",
      "x": 814,
      "y": 250,
      "width": 270,
      "height": 248,
      "offsetX": 0,
      "offsetY": 0
    },
    {
      "id": "runR_19",
      "x": 1085,
      "y": 250,
      "width": 270,
      "height": 248,
      "offsetX": 0,
      "offsetY": 0
    },
    {
      "id": "runR_20",
      "x": 1356,
      "y": 250,
      "width": 270,
      "height": 248,
      "offsetX": 0,
      "offsetY": 0
    },
    {
      "id": "runR_21",
      "x": 1627,
      "y": 250,
      "width": 270,
      "height": 248,
      "offsetX": 0,
      "offsetY": 0
    },
    {
      "id": "runR_22",
      "x": 1898,
      "y": 250,
      "width": 270,
      "height": 248,
      "offsetX": 0,
      "offsetY": 0
    },
    {
      "id": "runR_23",
      "x": 2169,
      "y": 250,
      "width": 270,
      "height": 248,
      "offsetX": 0,
      "offsetY": 0
    },
    {
      "id": "runR_24",
      "x": 2440,
      "y": 250,
      "width": 270,
      "height": 248,
      "offsetX": 0,
      "offsetY": 0
    },
    {
      "id": "runR_25",
      "x": 2711,
      "y": 250,
      "width": 270,
      "height": 248,
      "offsetX": 0,
      "offsetY": 0
    },
    {
      "id": "runR_26",
      "x": 2982,
      "y": 250,
      "width": 270,
      "height": 248,
      "offsetX": 0,
      "offsetY": 0
    },
    {
      "id": "runR_27",
      "x": 3253,
      "y": 250,
      "width": 270,
      "height": 248,
      "offsetX": 0,
      "offsetY": 0
    },
    {
      "id": "runR_28",
      "x": 3524,
      "y": 250,
      "width": 270,
      "height": 248,
      "offsetX": 0,
      "offsetY": 0
    },
    {
      "id": "runR_29",
      "x": 3795,
      "y": 250,
      "width": 270,
      "height": 248,
      "offsetX": 0,
      "offsetY": 0
    },
    {
      "id": "runR_30",
      "x": 1,
      "y": 499,
      "width": 270,
      "height": 248,
      "offsetX": 0,
      "offsetY": 0
    },
    {
      "id": "runR_31",
      "x": 272,
      "y": 499,
      "width": 270,
      "height": 248,
      "offsetX": 0,
      "offsetY": 0
    },
    {
      "id": "runR_32",
      "x": 543,
      "y": 499,
      "width": 270,
      "height": 248,
      "offsetX": 0,
      "offsetY": 0
    },
    {
      "id": "runR_33",
      "x": 814,
      "y": 499,
      "width": 270,
      "height": 248,
      "offsetX": 0,
      "offsetY": 0
    },
    {
      "id": "runR_34",
      "x": 1085,
      "y": 499,
      "width": 270,
      "height": 248,
      "offsetX": 0,
      "offsetY": 0
    },
    {
      "id": "runR_35",
      "x": 1356,
      "y": 499,
      "width": 270,
      "height": 248,
      "offsetX": 0,
      "offsetY": 0
    }
  ],
  "frameOrder": [
    "runR_0",
    "runR_1",
    "runR_2",
    "runR_3",
    "runR_4",
    "runR_5",
    "runR_6",
    "runR_7",
    "runR_8",
    "runR_9",
    "runR_10",
    "runR_11",
    "runR_12",
    "runR_13",
    "runR_14",
    "runR_15",
    "runR_16",
    "runR_17",
    "runR_18",
    "runR_19",
    "runR_20",
    "runR_21",
    "runR_22",
    "runR_23",
    "runR_24",
    "runR_25",
    "runR_26",
    "runR_27",
    "runR_28",
    "runR_29",
    "runR_30",
    "runR_31",
    "runR_32",
    "runR_33",
    "runR_34",
    "runR_35"
  ],
  "duplicates": {},
  "fps": 60
}