{
  "version": 1,
  "animation": "appearL",
  "width": 55,
  "height": 47,
  "offsetX": -13.1,
  "offsetY": 0,
  "frames": [
    {
      "id": "appearL_0",
      "x": 1,
      "y": 1,
      "width": 26,
      "height": 45,
      "offsetX": 0,
      "offsetY": 0
    },
    {
      "id": "appearL_8",
      "x": 28,
      "y": 1,
      "width": 26,
      "height": 45,
      "offsetX": 0,
      "offsetY": 0
    }
  ],
  "frameOrder": [
    "appearL_0",
    "appearL_1",
    "appearL_2",
    "appearL_3",
    "appearL_4",
    "appearL_5",
    "appearL_6",
    "appearL_7",
    "appearL_8",
    "appearL_9",
    "appearL_10",
    "appearL_11",
    "appearL_12",
    "appearL_13",
    "appearL_14",
    "appearL_15",
    "appearL_16",
    "appearL_17",
    "appearL_18",
    "appearL_19",
    "appearL_20"
  ],
  "duplicates": {
    "appearL_1": "appearL_0",
    "appearL_2": "appearL_0",
    "appearL_3": "appearL_0",
    "appearL_4": "appearL_0",
    "appearL_5": "appearL_0",
    "appearL_6": "appearL_0",
    "appearL_7": "appearL_0",
    "appearL_9": "appearL_8",
    "appearL_10": "appearL_8",
    "appearL_11": "appearL_8",
    "appearL_12": "appearL_8",
    "appearL_13": "appearL_8",
    "appearL_14": "appearL_8",
    "appearL_15": "appearL_8",
    "appearL_16": "appearL_8",
    "appearL_17": "appearL_8",
    "appearL_18": "appearL_8",
    "appearL_19": "appearL_8",
    "appearL_20": "appearL_8"
  },
  "fps": 60
}