{
  "version": 1,
  "animation": "anim14R",
  "width": 3125,
  "height": 73,
  "offsetX": -36.45,
  "offsetY": 0,
  "frames": [
    {
      "id": "anim14R_0",
      "x": 1,
      "y": 1,
      "width": 70,
      "height": 71,
      "offsetX": 0,
      "offsetY": 0
    },
    {
      "id": "anim14R_1",
      "x": 72,
      "y": 1,
      "width": 70,
      "height": 71,
      "offsetX": 0,
      "offsetY": 0
    },
    {
      "id": "anim14R_2",
      "x": 143,
      "y": 1,
      "width": 70,
      "height": 71,
      "offsetX": 0,
      "offsetY": 0
    },
    {
      "id": "anim14R_3",
      "x": 214,
      "y": 1,
      "width": 70,
      "height": 71,
      "offsetX": 0,
      "offsetY": 0
    },
    {
      "id": "anim14R_4",
      "x": 285,
      "y": 1,
      "width": 70,
      "height": 71,
      "offsetX": 0,
      "offsetY": 0
    },
    {
      "id": "anim14R_5",
      "x": 356,
      "y": 1,
      "width": 70,
      "height": 71,
      "offsetX": 0,
      "offsetY": 0
    },
    {
      "id": "anim14R_6",
      "x": 427,
      "y": 1,
      "width": 70,
      "height": 71,
      "offsetX": 0,
      "offsetY": 0
    },
    {
      "id": "anim14R_7",
      "x": 498,
      "y": 1,
      "width": 70,
      "height": 71,
      "offsetX": 0,
      "offsetY": 0
    },
    {
      "id": "anim14R_8",
      "x": 569,
      "y": 1,
      "width": 70,
      "height": 71,
      "offsetX": 0,
      "offsetY": 0
    },
    {
      "id": "anim14R_9",
      "x": 640,
      "y": 1,
      "width": 70,
      "height": 71,
      "offsetX": 0,
      "offsetY": 0
    },
    {
      "id": "anim14R_10",
      "x": 711,
      "y": 1,
      "width": 70,
      "height": 71,
      "offsetX": 0,
      "offsetY": 0
    },
    {
      "id": "anim14R_11",
      "x": 782,
      "y": 1,
      "width": 70,
      "height": 71,
      "offsetX": 0,
      "offsetY": 0
    },
    {
      "id": "anim14R_12",
      "x": 853,
      "y": 1,
      "width": 70,
      "height": 71,
      "offsetX": 0,
      "offsetY": 0
    },
    {
      "id": "anim14R_13",
      "x": 924,
      "y": 1,
      "width": 70,
      "height": 71,
      "offsetX": 0,
      "offsetY": 0
    },
    {
      "id": "anim14R_14",
      "x": 995,
      "y": 1,
      "width": 70,
      "height": 71,
      "offsetX": 0,
      "offsetY": 0
    },
    {
      "id": "anim14R_15",
      "x": 1066,
      "y": 1,
      "width": 70,
      "height": 71,
      "offsetX": 0,
      "offsetY": 0
    },
    {
      "id": "anim14R_16",
      "x": 1137,
      "y": 1,
      "width": 70,
      "height": 71,
      "offsetX": 0,
      "offsetY": 0
    },
    {
      "id": "anim14R_17",
      "x": 1208,
      "y": 1,
      "width": 70,
      "height": 71,
      "offsetX": 0,
      "offsetY": 0
    },
    {
      "id": "anim14R_18",
      "x": 1279,
      "y": 1,
      "width": 70,
      "height": 71,
      "offsetX": 0,
      "offsetY": 0
    },
    {
      "id": "anim14R_21",
      "x": 1350,
      "y": 1,
      "width": 70,
      "height": 71,
      "offsetX": 0,
      "offsetY": 0
    },
    {
      "id": "anim14R_22",
      "x": 1421,
      "y": 1,
      "width": 70,
      "height": 71,
      "offsetX": 0,
      "offsetY": 0
    },
    {
      "id": "anim14R_23",
      "x": 1492,
      "y": 1,
      "width": 70,
      "height": 71,
      "offsetX": 0,
      "offsetY": 0
    },
    {
      "id": "anim14R_24",
      "x": 1563,
      "y": 1,
      "width": 70,
      "height": 71,
      "offsetX": 0,
      "offsetY": 0
    },
    {
      "id": "anim14R_25",
      "x": 1634,
      "y": 1,
      "width": 70,
      "height": 71,
      "offsetX": 0,
      "offsetY": 0
    },
    {
      "id": "anim14R_26",
      "x": 1705,
      "y": 1,
      "width": 70,
      "height": 71,
      "offsetX": 0,
      "offsetY": 0
    },
    {
      "id": "anim14R_27",
      "x": 1776,
      "y": 1,
      "width": 70,
      "height": 71,
      "offsetX": 0,
      "offsetY": 0
    },
    {
      "id": "anim14R_28",
      "x": 1847,
      "y": 1,
      "width": 70,
      "height": 71,
      "offsetX": 0,
      "offsetY": 0
    },
    {
      "id": "anim14R_29",
      "x": 1918,
      "y": 1,
      "width": 70,
      "height": 71,
      "offsetX": 0,
      "offsetY": 0
    },
    {
      "id": "anim14R_30",
      "x": 1989,
      "y": 1,
      "width": 70,
      "height": 71,
      "offsetX": 0,
      "offsetY": 0
    },
    {
      "id": "anim14R_31",
      "x": 2060,
      "y": 1,
      "width": 70,
      "height": 71,
      "offsetX": 0,
      "offsetY": 0
    },
    {
      "id": "anim14R_32",
      "x": 2131,
      "y": 1,
      "width": 70,
      "height": 71,
      "offsetX": 0,
      "offsetY": 0
    },
    {
      "id": "anim14R_33",
      "x": 2202,
      "y": 1,
      "width": 70,
      "height": 71,
      "offsetX": 0,
      "offsetY": 0
    },
    {
      "id": "anim14R_34",
      "x": 2273,
      "y": 1,
      "width": 70,
      "height": 71,
      "offsetX": 0,
      "offsetY": 0
    },
    {
      "id": "anim14R_35",
      "x": 2344,
      "y": 1,
      "width": 70,
      "height": 71,
      "offsetX": 0,
      "offsetY": 0
    },
    {
      "id": "anim14R_36",
      "x": 2415,
      "y": 1,
      "width": 70,
      "height": 71,
      "offsetX": 0,
      "offsetY": 0
    },
    {
      "id": "anim14R_37",
      "x": 2486,
      "y": 1,
      "width": 70,
      "height": 71,
      "offsetX": 0,
      "offsetY": 0
    },
    {
      "id": "anim14R_38",
      "x": 2557,
      "y": 1,
      "width": 70,
      "height": 71,
      "offsetX": 0,
      "offsetY": 0
    },
    {
      "id": "anim14R_39",
      "x": 2628,
      "y": 1,
      "width": 70,
      "height": 71,
      "offsetX": 0,
      "offsetY": 0
    },
    {
      "id": "anim14R_40",
      "x": 2699,
      "y": 1,
      "width": 70,
      "height": 71,
      "offsetX": 0,
      "offsetY": 0
    },
    {
      "id": "anim14R_41",
      "x": 2770,
      "y": 1,
      "width": 70,
      "height": 71,
      "offsetX": 0,
      "offsetY": 0
    },
    {
      "id": "anim14R_42",
      "x": 2841,
      "y": 1,
      "width": 70,
      "height": 71,
      "offsetX": 0,
      "offsetY": 0
    },
    {
      "id": "anim14R_43",
      "x": 2912,
      "y": 1,
      "width": 70,
      "height": 71,
      "offsetX": 0,
      "offsetY": 0
    },
    {
      "id": "anim14R_44",
      "x": 2983,
      "y": 1,
      "width": 70,
      "height": 71,
      "offsetX": 0,
      "offsetY": 0
    },
    {
      "id": "anim14R_45",
      "x": 3054,
      "y": 1,
      "width": 70,
      "height": 71,
      "offsetX": 0,
      "offsetY": 0
    }
  ],
  "frameOrder": [
    "anim14R_0",
    "anim14R_1",
    "anim14R_2",
    "anim14R_3",
    "anim14R_4",
    "anim14R_5",
    "anim14R_6",
    "anim14R_7",
    "anim14R_8",
    "anim14R_9",
    "anim14R_10",
    "anim14R_11",
    "anim14R_12",
    "anim14R_13",
    "anim14R_14",
    "anim14R_15",
    "anim14R_16",
    "anim14R_17",
    "anim14R_18",
    "anim14R_19",
    "anim14R_20",
    "anim14R_21",
    "anim14R_22",
    "anim14R_23",
    "anim14R_24",
    "anim14R_25",
    "anim14R_26",
    "anim14R_27",
    "anim14R_28",
    "anim14R_29",
    "anim14R_30",
    "anim14R_31",
    "anim14R_32",
    "anim14R_33",
    "anim14R_34",
    "anim14R_35",
    "anim14R_36",
    "anim14R_37",
    "anim14R_38",
    "anim14R_39",
    "anim14R_40",
    "anim14R_41",
    "anim14R_42",
    "anim14R_43",
    "anim14R_44",
    "anim14R_45",
    "anim14R_46",
    "anim14R_47",
    "anim14R_48",
    "anim14R_49",
    "anim14R_50",
    "anim14R_51",
    "anim14R_52",
    "anim14R_53",
    "anim14R_54",
    "anim14R_55",
    "anim14R_56",
    "anim14R_57",
    "anim14R_58",
    "anim14R_59"
  ],
  "duplicates": {
    "anim14R_19": "anim14R_18",
    "anim14R_20": "anim14R_18",
    "anim14R_46": "anim14R_45",
    "anim14R_47": "anim14R_45",
    "anim14R_48": "anim14R_45",
    "anim14R_49": "anim14R_45",
    "anim14R_50": "anim14R_45",
    "anim14R_51": "anim14R_45",
    "anim14R_52": "anim14R_45",
    "anim14R_53": "anim14R_45",
    "anim14R_54": "anim14R_45",
    "anim14R_55": "anim14R_45",
    "anim14R_56": "anim14R_45",
    "anim14R_57": "anim14R_45",
    "anim14R_58": "anim14R_45",
    "anim14R_59": "anim14R_45"
  },
  "fps": 60
}