{
  "version": 1,
  "animation": "appearR",
  "width": 4048,
  "height": 297,
  "offsetX": 0,
  "offsetY": 0,
  "frames": [
    {
      "id": "appearR_0",
      "x": 1,
      "y": 1,
      "width": 70,
      "height": 147,
      "offsetX": 0,
      "offsetY": 0
    },
    {
      "id": "appearR_1",
      "x": 72,
      "y": 1,
      "width": 70,
      "height": 147,
      "offsetX": 0,
      "offsetY": 0
    },
    {
      "id": "appearR_2",
      "x": 143,
      "y": 1,
      "width": 70,
      "height": 147,
      "offsetX": 0,
      "offsetY": 0
    },
    {
      "id": "appearR_3",
      "x": 214,
      "y": 1,
      "width": 70,
      "height": 147,
      "offsetX": 0,
      "offsetY": 0
    },
    {
      "id": "appearR_4",
      "x": 285,
      "y": 1,
      "width": 70,
      "height": 147,
      "offsetX": 0,
      "offsetY": 0
    },
    {
      "id": "appearR_5",
      "x": 356,
      "y": 1,
      "width": 70,
      "height": 147,
      "offsetX": 0,
      "offsetY": 0
    },
    {
      "id": "appearR_6",
      "x": 427,
      "y": 1,
      "width": 70,
      "height": 147,
      "offsetX": 0,
      "offsetY": 0
    },
    {
      "id": "appearR_7",
      "x": 498,
      "y": 1,
      "width": 70,
      "height": 147,
      "offsetX": 0,
      "offsetY": 0
    },
    {
      "id": "appearR_8",
      "x": 569,
      "y": 1,
      "width": 70,
      "height": 147,
      "offsetX": 0,
      "offsetY": 0
    },
    {
      "id": "appearR_9",
      "x": 640,
      "y": 1,
      "width": 70,
      "height": 147,
      "offsetX": 0,
      "offsetY": 0
    },
    {
      "id": "appearR_10",
      "x": 711,
      "y": 1,
      "width": 70,
      "height": 147,
      "offsetX": 0,
      "offsetY": 0
    },
    {
      "id": "appearR_11",
      "x": 782,
      "y": 1,
      "width": 70,
      "height": 147,
      "offsetX": 0,
      "offsetY": 0
    },
    {
      "id": "appearR_12",
      "x": 853,
      "y": 1,
      "width": 70,
      "height": 147,
      "offsetX": 0,
      "offsetY": 0
    },
    {
      "id": "appearR_13",
      "x": 924,
      "y": 1,
      "width": 70,
      "height": 147,
      "offsetX": 0,
      "offsetY": 0
    },
    {
      "id": "appearR_14",
      "x": 995,
      "y": 1,
      "width": 70,
      "height": 147,
      "offsetX": 0,
      "offsetY": 0
    },
    {
      "id": "appearR_15",
      "x": 1066,
      "y": 1,
      "width": 70,
      "height": 147,
      "offsetX": 0,
      "offsetY": 0
    },
    {
      "id": "appearR_16",
      "x": 1137,
      "y": 1,
      "width": 70,
      "height": 147,
      "offsetX": 0,
      "offsetY": 0
    },
    {
      "id": "appearR_17",
      "x": 1208,
      "y": 1,
      "width": 70,
      "height": 147,
      "offsetX": 0,
      "offsetY": 0
    },
    {
      "id": "appearR_18",
      "x": 1279,
      "y": 1,
      "width": 70,
      "height": 147,
      "offsetX": 0,
      "offsetY": 0
    },
    {
      "id": "appearR_19",
      "x": 1350,
      "y": 1,
      "width": 70,
      "height": 147,
      "offsetX": 0,
      "offsetY": 0
    },
    {
      "id": "appearR_20",
      "x": 1421,
      "y": 1,
      "width": 70,
      "height": 147,
      "offsetX": 0,
      "offsetY": 0
    },
    {
      "id": "appearR_21",
      "x": 1492,
      "y": 1,
      "width": 70,
      "height": 147,
      "offsetX": 0,
      "offsetY": 0
    },
    {
      "id": "appearR_22",
      "x": 1563,
      "y": 1,
      "width": 70,
      "height": 147,
      "offsetX": 0,
      "offsetY": 0
    },
    {
      "id": "appearR_23",
      "x": 1634,
      "y": 1,
      "width": 70,
      "height": 147,
      "offsetX": 0,
      "offsetY": 0
    },
    {
      "id": "appearR_24",
      "x": 1705,
      "y": 1,
      "width": 70,
      "height": 147,
      "offsetX": 0,
      "offsetY": 0
    },
    {
      "id": "appearR_25",
      "x": 1776,
      "y": 1,
      "width": 70,
      "height": 147,
      "offsetX": 0,
      "offsetY": 0
    },
    {
      "id": "appearR_26",
      "x": 1847,
      "y": 1,
      "width": 70,
      "height": 147,
      "offsetX": 0,
      "offsetY": 0
    },
    {
      "id": "appearR_27",
      "x": 1918,
      "y": 1,
      "width": 70,
      "height": 147,
      "offsetX": 0,
      "offsetY": 0
    },
    {
      "id": "appearR_28",
      "x": 1989,
      "y": 1,
      "width": 70,
      "height": 147,
      "offsetX": 0,
      "offsetY": 0
    },
    {
      "id": "appearR_29",
      "x": 2060,
      "y": 1,
      "width": 70,
      "height": 147,
      "offsetX": 0,
      "offsetY": 0
    },
    {
      "id": "appearR_30",
      "x": 2131,
      "y": 1,
      "width": 70,
      "height": 147,
      "offsetX": 0,
      "offsetY": 0
    },
    {
      "id": "appearR_31",
      "x": 2202,
      "y": 1,
      "width": 70,
      "height": 147,
      "offsetX": 0,
      "offsetY": 0
    },
    {
      "id": "appearR_32",
      "x": 2273,
      "y": 1,
      "width": 70,
      "height": 147,
      "offsetX": 0,
      "offsetY": 0
    },
    {
      "id": "appearR_33",
      "x": 2344,
      "y": 1,
      "width": 70,
      "height": 147,
      "offsetX": 0,
      "offsetY": 0
    },
    {
      "id": "appearR_34",
      "x": 2415,
      "y": 1,
      "width": 70,
      "height": 147,
      "offsetX": 0,
      "offsetY": 0
    },
    {
      "id": "appearR_35",
      "x": 2486,
      "y": 1,
      "width": 70,
      "height": 147,
      "offsetX": 0,
      "offsetY": 0
    },
    {
      "id": "appearR_36",
      "x": 2557,
      "y": 1,
      "width": 70,
      "height": 147,
      "offsetX": 0,
      "offsetY": 0
    },
    {
      "id": "appearR_37",
      "x": 2628,
      "y": 1,
      "width": 70,
      "height": 147,
      "offsetX": 0,
      "offsetY": 0
    },
    {
      "id": "appearR_38",
      "x": 2699,
      "y": 1,
      "width": 70,
      "height": 147,
      "offsetX": 0,
      "offsetY": 0
    },
    {
      "id": "appearR_39",
      "x": 2770,
      "y": 1,
      "width": 70,
      "height": 147,
      "offsetX": 0,
      "offsetY": 0
    },
    {
      "id": "appearR_40",
      "x": 2841,
      "y": 1,
      "width": 70,
      "height": 147,
      "offsetX": 0,
      "offsetY": 0
    },
    {
      "id": "appearR_41",
      "x": 2912,
      "y": 1,
      "width": 70,
      "height": 147,
      "offsetX": 0,
      "offsetY": 0
    },
    {
      "id": "appearR_42",
      "x": 2983,
      "y": 1,
      "width": 70,
      "height": 147,
      "offsetX": 0,
      "offsetY": 0
    },
    {
      "id": "appearR_43",
      "x": 3054,
      "y": 1,
      "width": 70,
      "height": 147,
      "offsetX": 0,
      "offsetY": 0
    },
    {
      "id": "appearR_44",
      "x": 3125,
      "y": 1,
      "width": 70,
      "height": 147,
      "offsetX": 0,
      "offsetY": 0
    },
    {
      "id": "appearR_45",
      "x": 3196,
      "y": 1,
      "width": 70,
      "height": 147,
      "offsetX": 0,
      "offsetY": 0
    },
    {
      "id": "appearR_46",
      "x": 3267,
      "y": 1,
      "width": 70,
      "height": 147,
      "offsetX": 0,
      "offsetY": 0
    },
    {
      "id": "appearR_47",
      "x": 3338,
      "y": 1,
      "width": 70,
      "height": 147,
      "offsetX": 0,
      "offsetY": 0
    },
    {
      "id": "appearR_48",
      "x": 3409,
      "y": 1,
      "width": 70,
      "height": 147,
      "offsetX": 0,
      "offsetY": 0
    },
    {
      "id": "appearR_49",
      "x": 3480,
      "y": 1,
      "width": 70,
      "height": 147,
      "offsetX": 0,
      "offsetY": 0
    },
    {
      "id": "appearR_50",
      "x": 3551,
      "y": 1,
      "width": 70,
      "height": 147,
      "offsetX": 0,
      "offsetY": 0
    },
    {
      "id": "appearR_51",
      "x": 3622,
      "y": 1,
      "width": 70,
      "height": 147,
      "offsetX": 0,
      "offsetY": 0
    },
    {
      "id": "appearR_52",
      "x": 3693,
      "y": 1,
      "width": 70,
      "height": 147,
      "offsetX": 0,
      "offsetY": 0
    },
    {
      "id": "appearR_53",
      "x": 3764,
      "y": 1,
      "width": 70,
      "height": 147,
      "offsetX": 0,
      "offsetY": 0
    },
    {
      "id": "appearR_54",
      "x": 3835,
      "y": 1,
      "width": 70,
      "height": 147,
      "offsetX": 0,
      "offsetY": 0
    },
    {
      "id": "appearR_55",
      "x": 3906,
      "y": 1,
      "width": 70,
      "height": 147,
      "offsetX": 0,
      "offsetY": 0
    },
    {
      "id": "appearR_56",
      "x": 3977,
      "y": 1,
      "width": 70,
      "height": 147,
      "offsetX": 0,
      "offsetY": 0
    },
    {
      "id": "appearR_57",
      "x": 1,
      "y": 149,
      "width": 70,
      "height": 147,
      "offsetX": 0,
      "offsetY": 0
    },
    {
      "id": "appearR_58",
      "x": 72,
      "y": 149,
      "width": 70,
      "height": 147,
      "offsetX": 0,
      "offsetY": 0
    },
    {
      "id": "appearR_59",
      "x": 143,
      "y": 149,
      "width": 70,
      "height": 147,
      "offsetX": 0,
      "offsetY": 0
    },
    {
      "id": "appearR_60",
      "x": 214,
      "y": 149,
      "width": 70,
      "height": 147,
      "offsetX": 0,
      "offsetY": 0
    },
    {
      "id": "appearR_61",
      "x": 285,
      "y": 149,
      "width": 70,
      "height": 147,
      "offsetX": 0,
      "offsetY": 0
    },
    {
      "id": "appearR_62",
      "x": 356,
      "y": 149,
      "width": 70,
      "height": 147,
      "offsetX": 0,
      "offsetY": 0
    },
    {
      "id": "appearR_63",
      "x": 427,
      "y": 149,
      "width": 70,
      "height": 147,
      "offsetX": 0,
      "offsetY": 0
    },
    {
      "id": "appearR_64",
      "x": 498,
      "y": 149,
      "width": 70,
      "height": 147,
      "offsetX": 0,
      "offsetY": 0
    },
    {
      "id": "appearR_65",
      "x": 569,
      "y": 149,
      "width": 70,
      "height": 147,
      "offsetX": 0,
      "offsetY": 0
    },
    {
      "id": "appearR_66",
      "x": 640,
      "y": 149,
      "width": 70,
      "height": 147,
      "offsetX": 0,
      "offsetY": 0
    },
    {
      "id": "appearR_67",
      "x": 711,
      "y": 149,
      "width": 70,
      "height": 147,
      "offsetX": 0,
      "offsetY": 0
    },
    {
      "id": "appearR_68",
      "x": 782,
      "y": 149,
      "width": 70,
      "height": 147,
      "offsetX": 0,
      "offsetY": 0
    },
    {
      "id": "appearR_69",
      "x": 853,
      "y": 149,
      "width": 70,
      "height": 147,
      "offsetX": 0,
      "offsetY": 0
    },
    {
      "id": "appearR_70",
      "x": 924,
      "y": 149,
      "width": 70,
      "height": 147,
      "offsetX": 0,
      "offsetY": 0
    },
    {
      "id": "appearR_71",
      "x": 995,
      "y": 149,
      "width": 70,
      "height": 147,
      "offsetX": 0,
      "offsetY": 0
    },
    {
      "id": "appearR_72",
      "x": 1066,
      "y": 149,
      "width": 70,
      "height": 147,
      "offsetX": 0,
      "offsetY": 0
    }
  ],
  "frameOrder": [
    "appearR_0",
    "appearR_1",
    "appearR_2",
    "appearR_3",
    "appearR_4",
    "appearR_5",
    "appearR_6",
    "appearR_7",
    "appearR_8",
    "appearR_9",
    "appearR_10",
    "appearR_11",
    "appearR_12",
    "appearR_13",
    "appearR_14",
    "appearR_15",
    "appearR_16",
    "appearR_17",
    "appearR_18",
    "appearR_19",
    "appearR_20",
    "appearR_21",
    "appearR_22",
    "appearR_23",
    "appearR_24",
    "appearR_25",
    "appearR_26",
    "appearR_27",
    "appearR_28",
    "appearR_29",
    "appearR_30",
    "appearR_31",
    "appearR_32",
    "appearR_33",
    "appearR_34",
    "appearR_35",
    "appearR_36",
    "appearR_37",
    "appearR_38",
    "appearR_39",
    "appearR_40",
    "appearR_41",
    "appearR_42",
    "appearR_43",
    "appearR_44",
    "appearR_45",
    "appearR_46",
    "appearR_47",
    "appearR_48",
    "appearR_49",
    "appearR_50",
    "appearR_51",
    "appearR_52",
    "appearR_53",
    "appearR_54",
    "appearR_55",
    "appearR_56",
    "appearR_57",
    "appearR_58",
    "appearR_59",
    "appearR_60",
    "appearR_61",
    "appearR_62",
    "appearR_63",
    "appearR_64",
    "appearR_65",
    "appearR_66",
    "appearR_67",
    "appearR_68",
    "appearR_69",
    "appearR_70",
    "appearR_71",
    "appearR_72",
    "appearR_73",
    "appearR_74"
  ],
  "duplicates": {
    "appearR_73": "appearR_72",
    "appearR_74": "appearR_72"
  },
  "fps": 60
}