{
  "version": 1,
  "animation": "dieL",
  "width": 2611,
  "height": 67,
  "offsetX": -50.05,
  "offsetY": 0,
  "frames": [
    {
      "id": "dieL_0",
      "x": 1,
      "y": 1,
      "width": 86,
      "height": 65,
      "offsetX": 0,
      "offsetY": 0
    },
    {
      "id": "dieL_6",
      "x": 88,
      "y": 1,
      "width": 86,
      "height": 65,
      "offsetX": 0,
      "offsetY": 0
    },
    {
      "id": "dieL_9",
      "x": 175,
      "y": 1,
      "width": 86,
      "height": 65,
      "offsetX": 0,
      "offsetY": 0
    },
    {
      "id": "dieL_22",
      "x": 262,
      "y": 1,
      "width": 86,
      "height": 65,
      "offsetX": 0,
      "offsetY": 0
    },
    {
      "id": "dieL_23",
      "x": 349,
      "y": 1,
      "width": 86,
      "height": 65,
      "offsetX": 0,
      "offsetY": 0
    },
    {
      "id": "dieL_24",
      "x": 436,
      "y": 1,
      "width": 86,
      "height": 65,
      "offsetX": 0,
      "offsetY": 0
    },
    {
      "id": "dieL_25",
      "x": 523,
      "y": 1,
      "width": 86,
      "height": 65,
      "offsetX": 0,
      "offsetY": 0
    },
    {
      "id": "dieL_26",
      "x": 610,
      "y": 1,
      "width": 86,
      "height": 65,
      "offsetX": 0,
      "offsetY": 0
    },
    {
      "id": "dieL_27",
      "x": 697,
      "y": 1,
      "width": 86,
      "height": 65,
      "offsetX": 0,
      "offsetY": 0
    },
    {
      "id": "dieL_30",
      "x": 784,
      "y": 1,
      "width": 86,
      "height": 65,
      "offsetX": 0,
      "offsetY": 0
    },
    {
      "id": "dieL_52",
      "x": 871,
      "y": 1,
      "width": 86,
      "height": 65,
      "offsetX": 0,
      "offsetY": 0
    },
    {
      "id": "dieL_53",
      "x": 958,
      "y": 1,
      "width": 86,
      "height": 65,
      "offsetX": 0,
      "offsetY": 0
    },
    {
      "id": "dieL_54",
      "x": 1045,
      "y": 1,
      "width": 86,
      "height": 65,
      "offsetX": 0,
      "offsetY": 0
    },
    {
      "id": "dieL_55",
      "x": 1132,
      "y": 1,
      "width": 86,
      "height": 65,
      "offsetX": 0,
      "offsetY": 0
    },
    {
      "id": "dieL_56",
      "x": 1219,
      "y": 1,
      "width": 86,
      "height": 65,
      "offsetX": 0,
      "offsetY": 0
    },
    {
      "id": "dieL_57",
      "x": 1306,
      "y": 1,
      "width": 86,
      "height": 65,
      "offsetX": 0,
      "offsetY": 0
    },
    {
      "id": "dieL_60",
      "x": 1393,
      "y": 1,
      "width": 86,
      "height": 65,
      "offsetX": 0,
      "offsetY": 0
    },
    {
      "id": "dieL_63",
      "x": 1480,
      "y": 1,
      "width": 86,
      "height": 65,
      "offsetX": 0,
      "offsetY": 0
    },
    {
      "id": "dieL_73",
      "x": 1567,
      "y": 1,
      "width": 86,
      "height": 65,
      "offsetX": 0,
      "offsetY": 0
    },
    {
      "id": "dieL_74",
      "x": 1654,
      "y": 1,
      "width": 86,
      "height": 65,
      "offsetX": 0,
      "offsetY": 0
    },
    {
      "id": "dieL_75",
      "x": 1741,
      "y": 1,
      "width": 86,
      "height": 65,
      "offsetX": 0,
      "offsetY": 0
    },
    {
      "id": "dieL_76",
      "x": 1828,
      "y": 1,
      "width": 86,
      "height": 65,
      "offsetX": 0,
      "offsetY": 0
    },
    {
      "id": "dieL_77",
      "x": 1915,
      "y": 1,
      "width": 86,
      "height": 65,
      "offsetX": 0,
      "offsetY": 0
    },
    {
      "id": "dieL_78",
      "x": 2002,
      "y": 1,
      "width": 86,
      "height": 65,
      "offsetX": 0,
      "offsetY": 0
    },
    {
      "id": "dieL_79",
      "x": 2089,
      "y": 1,
      "width": 86,
      "height": 65,
      "offsetX": 0,
      "offsetY": 0
    },
    {
      "id": "dieL_80",
      "x": 2176,
      "y": 1,
      "width": 86,
      "height": 65,
      "offsetX": 0,
      "offsetY": 0
    },
    {
      "id": "dieL_81",
      "x": 2263,
      "y": 1,
      "width": 86,
      "height": 65,
      "offsetX": 0,
      "offsetY": 0
    },
    {
      "id": "dieL_82",
      "x": 2350,
      "y": 1,
      "width": 86,
      "height": 65,
      "offsetX": 0,
      "offsetY": 0
    },
    {
      "id": "dieL_83",
      "x": 2437,
      "y": 1,
      "width": 86,
      "height": 65,
      "offsetX": 0,
      "offsetY": 0
    },
    {
      "id": "dieL_84",
      "x": 2524,
      "y": 1,
      "width": 86,
      "height": 65,
      "offsetX": 0,
      "offsetY": 0
    }
  ],
  "frameOrder": [
    "dieL_0",
    "dieL_1",
    "dieL_2",
    "dieL_3",
    "dieL_4",
    "dieL_5",
    "dieL_6",
    "dieL_7",
    "dieL_8",
    "dieL_9",
    "dieL_10",
    "dieL_11",
    "dieL_12",
    "dieL_13",
    "dieL_14",
    "dieL_15",
    "dieL_16",
    "dieL_17",
    "dieL_18",
    "dieL_19",
    "dieL_20",
    "dieL_21",
    "dieL_22",
    "dieL_23",
    "dieL_24",
    "dieL_25",
    "dieL_26",
    "dieL_27",
    "dieL_28",
    "dieL_29",
    "dieL_30",
    "dieL_31",
    "dieL_32",
    "dieL_33",
    "dieL_34",
    "dieL_35",
    "dieL_36",
    "dieL_37",
    "dieL_38",
    "dieL_39",
    "dieL_40",
    "dieL_41",
    "dieL_42",
    "dieL_43",
    "dieL_44",
    "dieL_45",
    "dieL_46",
    "dieL_47",
    "dieL_48",
    "dieL_49",
    "dieL_50",
    "dieL_51",
    "dieL_52",
    "dieL_53",
    "dieL_54",
    "dieL_55",
    "dieL_56",
    "dieL_57",
    "dieL_58",
    "dieL_59",
    "dieL_60",
    "dieL_61",
    "dieL_62",
    "dieL_63",
    "dieL_64",
    "dieL_65",
    "dieL_66",
    "dieL_67",
    "dieL_68",
    "dieL_69",
    "dieL_70",
    "dieL_71",
    "dieL_72",
    "dieL_73",
    "dieL_74",
    "dieL_75",
    "dieL_76",
    "dieL_77",
    "dieL_78",
    "dieL_79",
    "dieL_80",
    "dieL_81",
    "dieL_82",
    "dieL_83",
    "dieL_84",
    "dieL_85",
    "dieL_86"
  ],
  "duplicates": {
    "dieL_1": "dieL_0",
    "dieL_2": "dieL_0",
    "dieL_3": "dieL_0",
    "dieL_4": "dieL_0",
    "dieL_5": "dieL_0",
    "dieL_7": "dieL_6",
    "dieL_8": "dieL_6",
    "dieL_10": "dieL_9",
    "dieL_11": "dieL_9",
    "dieL_12": "dieL_9",
    "dieL_13": "dieL_9",
    "dieL_14": "dieL_9",
    "dieL_15": "dieL_9",
    "dieL_16": "dieL_9",
    "dieL_17": "dieL_9",
    "dieL_18": "dieL_9",
    "dieL_19": "dieL_9",
    "dieL_20": "dieL_9",
    "dieL_21": "dieL_9",
    "dieL_28": "dieL_27",
    "dieL_29": "dieL_27",
    "dieL_31": "dieL_30",
    "dieL_32": "dieL_30",
    "dieL_33": "dieL_27",
    "dieL_34": "dieL_27",
    "dieL_35": "dieL_27",
    "dieL_36": "dieL_30",
    "dieL_37": "dieL_30",
    "dieL_38": "dieL_30",
    "dieL_39": "dieL_27",
    "dieL_40": "dieL_27",
    "dieL_41": "dieL_27",
    "dieL_42": "dieL_30",
    "dieL_43": "dieL_30",
    "dieL_44": "dieL_30",
    "dieL_45": "dieL_27",
    "dieL_46": "dieL_27",
    "dieL_47": "dieL_27",
    "dieL_48": "dieL_30",
    "dieL_49": "dieL_30",
    "dieL_50": "dieL_30",
    "dieL_51": "dieL_27",
    "dieL_58": "dieL_57",
    "dieL_59": "dieL_57",
    "dieL_61": "dieL_60",
    "dieL_62": "dieL_60",
    "dieL_64": "dieL_63",
    "dieL_65": "dieL_63",
    "dieL_66": "dieL_63",
    "dieL_67": "dieL_63",
    "dieL_68": "dieL_63",
    "dieL_69": "dieL_63",
    "dieL_70": "dieL_63",
    "dieL_71": "dieL_63",
    "dieL_72": "dieL_63",
    "dieL_85": "dieL_84",
    "dieL_86": "dieL_84"
  },
  "fps": 60
}