{
  "version": 1,
  "animation": "runF",
  "width": 973,
  "height": 88,
  "offsetX": -34.6,
  "offsetY": 0,
  "frames": [
    {
      "id": "runF_0",
      "x": 1,
      "y": 1,
      "width": 80,
      "height": 86,
      "offsetX": 0,
      "offsetY": 0
    },
    {
      "id": "runF_1",
      "x": 82,
      "y": 1,
      "width": 80,
      "height": 86,
      "offsetX": 0,
      "offsetY": 0
    },
    {
      "id": "runF_2",
      "x": 163,
      "y": 1,
      "width": 80,
      "height": 86,
      "offsetX": 0,
      "offsetY": 0
    },
    {
      "id": "runF_3",
      "x": 244,
      "y": 1,
      "width": 80,
      "height": 86,
      "offsetX": 0,
      "offsetY": 0
    },
    {
      "id": "runF_4",
      "x": 325,
      "y": 1,
      "width": 80,
      "height": 86,
      "offsetX": 0,
      "offsetY": 0
    },
    {
      "id": "runF_5",
      "x": 406,
      "y": 1,
      "width": 80,
      "height": 86,
      "offsetX": 0,
      "offsetY": 0
    },
    {
      "id": "runF_6",
      "x": 487,
      "y": 1,
      "width": 80,
      "height": 86,
      "offsetX": 0,
      "offsetY": 0
    },
    {
      "id": "runF_7",
      "x": 568,
      "y": 1,
      "width": 80,
      "height": 86,
      "offsetX": 0,
      "offsetY": 0
    },
    {
      "id": "runF_8",
      "x": 649,
      "y": 1,
      "width": 80,
      "height": 86,
      "offsetX": 0,
      "offsetY": 0
    },
    {
      "id": "runF_9",
      "x": 730,
      "y": 1,
      "width": 80,
      "height": 86,
      "offsetX": 0,
      "offsetY": 0
    },
    {
      "id": "runF_10",
      "x": 811,
      "y": 1,
      "width": 80,
      "height": 86,
      "offsetX": 0,
      "offsetY": 0
    },
    {
      "id": "runF_11",
      "x": 892,
      "y": 1,
      "width": 80,
      "height": 86,
      "offsetX": 0,
      "offsetY": 0
    }
  ],
  "frameOrder": [
    "runF_0",
    "runF_1",
    "runF_2",
    "runF_3",
    "runF_4",
    "runF_5",
    "runF_6",
    "runF_7",
    "runF_8",
    "runF_9",
    "runF_10",
    "runF_11"
  ],
  "duplicates": {},
  "fps": 60
}